LICENSE
MANIFEST.in
README.rst
setup.py
django_floppymaterial.egg-info/PKG-INFO
django_floppymaterial.egg-info/SOURCES.txt
django_floppymaterial.egg-info/dependency_links.txt
django_floppymaterial.egg-info/top_level.txt
floppymaterial/__init__.py
floppymaterial/templates/floppymaterial/submit.html
floppymaterial/templates/floppymaterial/layouts/materialize.html
floppymaterial/templates/floppymaterial/rows/materialize.html