Metadata-Version: 1.1
Name: django-floppymaterial
Version: 0.2.1
Summary: A simple Django app to provide Materialize support to Floppy Forms.
Home-page: http://https://bitbucket.org/CodedInternet/django-floppymaterial/
Author: Tom Price
Author-email: tom@codedinternet.com
License: BSD License
Platform: UNKNOWN
Classifier: Environment :: Web Environment
Classifier: Framework :: Django
Classifier: Intended Audience :: Developers
Classifier: License :: OSI Approved :: MIT License
Classifier: Operating System :: OS Independent
Classifier: Programming Language :: Python
Classifier: Programming Language :: Python :: 3
Classifier: Programming Language :: Python :: 3.2
Classifier: Programming Language :: Python :: 3.3
Classifier: Topic :: Internet :: WWW/HTTP
Classifier: Topic :: Internet :: WWW/HTTP :: Dynamic Content
